{
  "updated": "2025-03-24T09:27:07.942Z",
  "count": 16,
  "items": [
    {
      "name": "꿰뚫어 찌르는 죽음의 가시 창",
      "price": 35000000,
      "date": "2025-03-24"
    },
    {
      "name": "나이트 랜스",
      "price": 60000,
      "date": "2025-03-24"
    },
    {
      "name": "나이트 랜스 R",
      "price": 7899999,
      "date": "2025-03-24"
    },
    {
      "name": "나이트브링어 스피어헤드",
      "price": 310000000,
      "date": "2025-03-24"
    },
    {
      "name": "데모닉 스케일아이 랜스",
      "price": 40000,
      "date": "2025-03-24"
    },
    {
      "name": "데모닉 스케일아이 랜스 R",
      "price": 20000000,
      "date": "2025-03-24"
    },
    {
      "name": "디바인 스몰 랜스",
      "price": 9000000,
      "date": "2025-03-24"
    },
    {
      "name": "라이온 크로 랜스",
      "price": 78000,
      "date": "2025-03-24"
    },
    {
      "name": "랑그히리스 본브레이커",
      "price": 5000000,
      "date": "2025-03-24"
    },
    {
      "name": "세인츠 가디언 랜스",
      "price": 30000000,
      "date": "2025-03-24"
    },
    {
      "name": "아투이의 랜스",
      "price": 1200000,
      "date": "2025-03-24"
    },
    {
      "name": "위벨의 지팡이(랜스) 레플리카",
      "price": 38880000,
      "date": "2025-03-24"
    },
    {
      "name": "초보자 라이온 크로 랜스",
      "price": 184800,
      "date": "2025-03-24"
    },
    {
      "name": "켈틱 잉곳 랜스",
      "price": 1000000,
      "date": "2025-03-24"
    },
    {
      "name": "페러시우스 게일 랜스",
      "price": 29900000,
      "date": "2025-03-24"
    },
    {
      "name": "피시스 우든 랜스",
      "price": 75000,
      "date": "2025-03-24"
    }
  ]
}