{
  "updated": "2025-03-29T09:24:53.757Z",
  "count": 5,
  "items": [
    {
      "name": "레드 에코스톤",
      "price": 78000,
      "date": "2025-03-29"
    },
    {
      "name": "블랙 에코스톤",
      "price": 79999,
      "date": "2025-03-29"
    },
    {
      "name": "블루 에코스톤",
      "price": 90000,
      "date": "2025-03-29"
    },
    {
      "name": "실버 에코스톤",
      "price": 79997,
      "date": "2025-03-29"
    },
    {
      "name": "옐로 에코스톤",
      "price": 79999,
      "date": "2025-03-29"
    }
  ]
}