{
  "updated": "2025-03-14T09:27:42.899Z",
  "count": 28,
  "items": [
    {
      "name": "강화된 금속판",
      "price": 1390000,
      "date": "2025-03-14"
    },
    {
      "name": "고대 정령의 화석",
      "price": 19000,
      "date": "2025-03-14"
    },
    {
      "name": "금광석",
      "price": 1100,
      "date": "2025-03-14"
    },
    {
      "name": "금광석 조각",
      "price": 250,
      "date": "2025-03-14"
    },
    {
      "name": "금괴",
      "price": 1755,
      "date": "2025-03-14"
    },
    {
      "name": "금판",
      "price": 4000,
      "date": "2025-03-14"
    },
    {
      "name": "니켈광석 조각",
      "price": 740,
      "date": "2025-03-14"
    },
    {
      "name": "동광석",
      "price": 500,
      "date": "2025-03-14"
    },
    {
      "name": "동광석 조각",
      "price": 600,
      "date": "2025-03-14"
    },
    {
      "name": "동괴",
      "price": 1644,
      "date": "2025-03-14"
    },
    {
      "name": "동판",
      "price": 3100,
      "date": "2025-03-14"
    },
    {
      "name": "미스릴광석",
      "price": 1190,
      "date": "2025-03-14"
    },
    {
      "name": "미스릴광석 조각",
      "price": 1200,
      "date": "2025-03-14"
    },
    {
      "name": "미스릴괴",
      "price": 1804,
      "date": "2025-03-14"
    },
    {
      "name": "미스릴판",
      "price": 3449,
      "date": "2025-03-14"
    },
    {
      "name": "아연광석 조각",
      "price": 269,
      "date": "2025-03-14"
    },
    {
      "name": "악마의 광석 조각",
      "price": 19998,
      "date": "2025-03-14"
    },
    {
      "name": "알 수 없는 광석 조각",
      "price": 900,
      "date": "2025-03-14"
    },
    {
      "name": "은광석",
      "price": 550,
      "date": "2025-03-14"
    },
    {
      "name": "은광석 조각",
      "price": 430,
      "date": "2025-03-14"
    },
    {
      "name": "은괴",
      "price": 1390,
      "date": "2025-03-14"
    },
    {
      "name": "은판",
      "price": 3500,
      "date": "2025-03-14"
    },
    {
      "name": "주석광석 조각",
      "price": 940,
      "date": "2025-03-14"
    },
    {
      "name": "철광석",
      "price": 340,
      "date": "2025-03-14"
    },
    {
      "name": "철광석 조각",
      "price": 370,
      "date": "2025-03-14"
    },
    {
      "name": "철괴",
      "price": 1000,
      "date": "2025-03-14"
    },
    {
      "name": "철판",
      "price": 990,
      "date": "2025-03-14"
    },
    {
      "name": "환상의 괴",
      "price": 93330,
      "date": "2025-03-14"
    }
  ]
}