{
  "updated": "2025-03-19T09:29:27.721Z",
  "count": 10,
  "items": [
    {
      "name": "골드 허브",
      "price": 299,
      "date": "2025-03-19"
    },
    {
      "name": "마나 허브",
      "price": 244,
      "date": "2025-03-19"
    },
    {
      "name": "만드레이크",
      "price": 419,
      "date": "2025-03-19"
    },
    {
      "name": "못쓰게 된 허브",
      "price": 82,
      "date": "2025-03-19"
    },
    {
      "name": "베이스 허브",
      "price": 296,
      "date": "2025-03-19"
    },
    {
      "name": "블러디 허브",
      "price": 278,
      "date": "2025-03-19"
    },
    {
      "name": "선라이트 허브",
      "price": 349,
      "date": "2025-03-19"
    },
    {
      "name": "포이즌 허브",
      "price": 350,
      "date": "2025-03-19"
    },
    {
      "name": "해독초",
      "price": 490,
      "date": "2025-03-19"
    },
    {
      "name": "화이트 허브",
      "price": 369,
      "date": "2025-03-19"
    }
  ]
}