{
  "updated": "2025-03-13T17:45:21.530Z",
  "count": 15,
  "items": [
    {
      "name": "강화된 스핀 기어",
      "price": 1450000,
      "date": "2025-03-13"
    },
    {
      "name": "고대 태양 무늬 스톤",
      "price": 998,
      "date": "2025-03-13"
    },
    {
      "name": "무른 힐웬 광석 조각",
      "price": 640,
      "date": "2025-03-13"
    },
    {
      "name": "반짝이는 힐웬",
      "price": 3000,
      "date": "2025-03-13"
    },
    {
      "name": "스핀 기어",
      "price": 21965,
      "date": "2025-03-13"
    },
    {
      "name": "에너지 증폭 장치",
      "price": 22390,
      "date": "2025-03-13"
    },
    {
      "name": "에너지 컨버터",
      "price": 4439,
      "date": "2025-03-13"
    },
    {
      "name": "에메랄드 코어",
      "price": 2490,
      "date": "2025-03-13"
    },
    {
      "name": "에메랄드 퓨즈",
      "price": 4500,
      "date": "2025-03-13"
    },
    {
      "name": "육각 너트",
      "price": 980,
      "date": "2025-03-13"
    },
    {
      "name": "육각 볼트",
      "price": 997,
      "date": "2025-03-13"
    },
    {
      "name": "융합된 힐웬 합금",
      "price": 503000,
      "date": "2025-03-13"
    },
    {
      "name": "힐웬",
      "price": 1640,
      "date": "2025-03-13"
    },
    {
      "name": "힐웬 광석 조각",
      "price": 250,
      "date": "2025-03-13"
    },
    {
      "name": "힐웬 합금",
      "price": 8197,
      "date": "2025-03-13"
    }
  ]
}