{
  "updated": "2025-03-28T09:29:50.731Z",
  "count": 17,
  "items": [
    {
      "name": "강화된 스핀 기어",
      "price": 1500000,
      "date": "2025-03-28"
    },
    {
      "name": "고대 태양 무늬 스톤",
      "price": 800,
      "date": "2025-03-28"
    },
    {
      "name": "고대 태양 무늬 스톤 조각",
      "price": 500,
      "date": "2025-03-28"
    },
    {
      "name": "무른 힐웬 광석 조각",
      "price": 900,
      "date": "2025-03-28"
    },
    {
      "name": "반짝이는 힐웬",
      "price": 1600,
      "date": "2025-03-28"
    },
    {
      "name": "순도 높은 융합의 힐웬 합금",
      "price": 70000000,
      "date": "2025-03-28"
    },
    {
      "name": "스핀 기어",
      "price": 13790,
      "date": "2025-03-28"
    },
    {
      "name": "에너지 증폭 장치",
      "price": 19992,
      "date": "2025-03-28"
    },
    {
      "name": "에너지 컨버터",
      "price": 4235,
      "date": "2025-03-28"
    },
    {
      "name": "에메랄드 코어",
      "price": 4400,
      "date": "2025-03-28"
    },
    {
      "name": "에메랄드 퓨즈",
      "price": 2998,
      "date": "2025-03-28"
    },
    {
      "name": "육각 너트",
      "price": 800,
      "date": "2025-03-28"
    },
    {
      "name": "육각 볼트",
      "price": 728,
      "date": "2025-03-28"
    },
    {
      "name": "융합된 힐웬 합금",
      "price": 399000,
      "date": "2025-03-28"
    },
    {
      "name": "힐웬",
      "price": 1400,
      "date": "2025-03-28"
    },
    {
      "name": "힐웬 광석 조각",
      "price": 295,
      "date": "2025-03-28"
    },
    {
      "name": "힐웬 합금",
      "price": 7200,
      "date": "2025-03-28"
    }
  ]
}